autodoc/__init__.py
autodoc/ai_enhancer.py
autodoc/ai_providers.py
autodoc/cli.py
autodoc/exporter.py
autodoc/framework_detector.py
autodoc/generator.py
autodoc/generator_languages.py
autodoc/languages.py
autodoc/scanner.py
autodoc/scanner_improved.py
autodoc/simple_js_scanner.py
autodoc/templates/README.md.j2
zerodoc_gen-1.4.4.dist-info/licenses/LICENSE
zerodoc_gen-1.4.4.dist-info/METADATA
zerodoc_gen-1.4.4.dist-info/WHEEL
zerodoc_gen-1.4.4.dist-info/entry_points.txt
zerodoc_gen-1.4.4.dist-info/top_level.txt
zerodoc_gen-1.4.4.dist-info/RECORD
