Metadata-Version: 2.4
Name: zerodoc-gen
Version: 1.4.4
Summary: Zero-config documentation generator with beautiful UI
Author-email: AutoDoc Team <ryan@ryankatayi.com>
License: MIT
Project-URL: Homepage, https://github.com/autodoc-team/autodoc-typer
Project-URL: Documentation, https://autodoc-typer.readthedocs.io
Project-URL: Repository, https://github.com/autodoc-team/autodoc-typer
Project-URL: Issues, https://github.com/autodoc-team/autodoc-typer/issues
Keywords: documentation,generator,python,typer,cli
Classifier: Development Status :: 3 - Alpha
Classifier: Intended Audience :: Developers
Classifier: License :: OSI Approved :: MIT License
Classifier: Programming Language :: Python :: 3
Classifier: Programming Language :: Python :: 3.8
Classifier: Programming Language :: Python :: 3.9
Classifier: Programming Language :: Python :: 3.10
Classifier: Programming Language :: Python :: 3.11
Classifier: Topic :: Documentation
Classifier: Topic :: Software Development :: Documentation
Requires-Python: >=3.8
License-File: LICENSE
Requires-Dist: typer[all]>=0.9.0
Requires-Dist: rich>=13.0.0
Requires-Dist: jinja2>=3.1.0
Requires-Dist: markdown-it-py>=3.0.0
Requires-Dist: tomli>=2.0.0; python_version < "3.11"
Requires-Dist: aiohttp>=3.8.0
Provides-Extra: dev
Requires-Dist: pytest>=7.4.0; extra == "dev"
Requires-Dist: pytest-cov>=4.1.0; extra == "dev"
Requires-Dist: black>=23.0.0; extra == "dev"
Requires-Dist: ruff>=0.1.0; extra == "dev"
Requires-Dist: mypy>=1.5.0; extra == "dev"
Dynamic: license-file
